{
  "creds": {
    "noiseKey": {
      "private": {
        "type": "Buffer",
        "data": "AOmpGzosg8OW3Aq3Cclwd27dCNkTvpQIhWMhP7U3Q3U="
      },
      "public": {
        "type": "Buffer",
        "data": "ISFv6seXPpWHd0/M3cVLnliINJ+vd/sH9iKZiMWVrDQ="
      }
    },
    "signedIdentityKey": {
      "private": {
        "type": "Buffer",
        "data": "WJfJYrlC5H5bC429nHGt9qmFxwAj7yzfahoEIwVUBXA="
      },
      "public": {
        "type": "Buffer",
        "data": "ja9J+/jJfP0vQAkwQvc3CEDpAwvMMEr4fBTo4ECY2G8="
      }
    },
    "signedPreKey": {
      "keyPair": {
        "private": {
          "type": "Buffer",
          "data": "yG/F+KnO/+XA5qAJW8w1+0WMq53fRXdKVYi6lX+9L3c="
        },
        "public": {
          "type": "Buffer",
          "data": "GhT627RVYWP38s8hq3FscJnZX/cKikhM2jOSnUHkjWY="
        }
      },
      "signature": {
        "type": "Buffer",
        "data": "ST4Q5Kk0VrkJwbX+ZE2F7SHgDRoeD1oOtO7CgV4DIDchjqW4/xLtcLxIq+Dl/+FEFwgE8rF1tZguP6Pj55rAAQ=="
      },
      "keyId": 1
    },
    "registrationId": 9,
    "advSecretKey": "d25qCAsvA01x0gmO8NYUUpJMt4XhR6ATVSkf9OiaHMs=",
    "processedHistoryMessages": [
      {
        "key": {
          "remoteJid": "62895335544695@s.whatsapp.net",
          "fromMe": true,
          "id": "05113B7F6194752617B9BDC4A0D3FD82"
        },
        "messageTimestamp": 1669629655
      },
      {
        "key": {
          "remoteJid": "62895335544695@s.whatsapp.net",
          "fromMe": true,
          "id": "7F6CFAC47A8D001CDFF9F04647E41B5F"
        },
        "messageTimestamp": 1669629656
      },
      {
        "key": {
          "remoteJid": "62895335544695@s.whatsapp.net",
          "fromMe": true,
          "id": "9742B95DEE5853B77B92AECD079722E9"
        },
        "messageTimestamp": 1669629706
      }
    ],
    "nextPreKeyId": 31,
    "firstUnuploadedPreKeyId": 31,
    "accountSettings": {
      "unarchiveChats": false
    },
    "account": {
      "details": "CN6bjhkQzY2SnAYYDg==",
      "accountSignatureKey": "V8QZNsZfLbKs6W74qpdIbpWqkbhMrE1/OrSBoRGpWX0=",
      "accountSignature": "RTM9wj+wYr2sNYtO0PlQO/R1w/9NnvJrd4J+fPTnEqEXLFMMhv1MZOdytnhS3hrX13joWE+zvhvKQzJhmQzeDQ==",
      "deviceSignature": "0pUHMKGPb814Q/mXCTJ0HxpcpLqK7ZcudmEkn33BTP7od67mEs5j065mYz0a/XQ6VSaKTyRuqD76xA96h4D2Cg=="
    },
    "me": {
      "id": "62895335544695:26@s.whatsapp.net",
      "name": "強い"
    },
    "signalIdentities": [
      {
        "identifier": {
          "name": "62895335544695:26@s.whatsapp.net",
          "deviceId": 0
        },
        "identifierKey": {
          "type": "Buffer",
          "data": "BVfEGTbGXy2yrOlu+KqXSG6VqpG4TKxNfzq0gaERqVl9"
        }
      }
    ],
    "platform": "android",
    "lastAccountSyncTimestamp": 1669629648,
    "myAppStateKeyId": "AAAAAMPr"
  },
  "keys": {
    "preKeys": {
      "1": {
        "private": {
          "type": "Buffer",
          "data": "0O4R+S6d45kitTGY1b9XXZ7oQ87Xg9FcGpP2EdNHQFs="
        },
        "public": {
          "type": "Buffer",
          "data": "uBHxZGvg0/fLvfGkO8RUYaqrErZIMyinHBoXQYwQDwk="
        }
      },
      "2": null,
      "3": {
        "private": {
          "type": "Buffer",
          "data": "QGSLUy3YJ9lpt6I1eEfTLx74VxSXAtMVNgAV6LSF1m8="
        },
        "public": {
          "type": "Buffer",
          "data": "1MUQ6wUyhD3Y/h53bT3acIi6rQvI7WxMs+lNJARUO0Y="
        }
      },
      "4": {
        "private": {
          "type": "Buffer",
          "data": "aHkFdCsu6jScRacq0LbFd6Dt1+RyiuMQX2Px5Xk5/ng="
        },
        "public": {
          "type": "Buffer",
          "data": "vOe9jrC77nhq+yu1YXUYGavVg1xkrCg3drrIV4cA+2U="
        }
      },
      "5": {
        "private": {
          "type": "Buffer",
          "data": "yASB6tfEIXeOiVPuGGsO5MVMd+PMmzgp1gi8KejH7GA="
        },
        "public": {
          "type": "Buffer",
          "data": "oZUJ54G9FfKVu/DQ9IOGbqlg5YwgwFTIbn6X0Bs07XE="
        }
      },
      "6": {
        "private": {
          "type": "Buffer",
          "data": "4OaaPia8+BjIV18LKmf/7iX6C6fPZi7uHuiyGYtraVk="
        },
        "public": {
          "type": "Buffer",
          "data": "Bf2YCRRI6dZM1KU94RmTklq+G2bfInX+iNAxkvGCwSc="
        }
      },
      "7": {
        "private": {
          "type": "Buffer",
          "data": "sJ7WFfPiUjwrXF7DSoNxrG2S5xoBj7Gp8QHLERPSvW4="
        },
        "public": {
          "type": "Buffer",
          "data": "AZeLo6Kva1ry8/jRC2u/O9iTPAOO4Im+/tYvBOfiuQs="
        }
      },
      "8": {
        "private": {
          "type": "Buffer",
          "data": "KNmf7VHiywHeamqUa6OJvqcdZn4ckAA6g99F2cKXx2Q="
        },
        "public": {
          "type": "Buffer",
          "data": "EknXxA5yH56shbVyZDM/PSv81eB2IjQy0jRqddiGSmQ="
        }
      },
      "9": null,
      "10": {
        "private": {
          "type": "Buffer",
          "data": "8G1+KjszFFruHsSnXNGt5DhqSRhDMzn9tFFAw0WSllE="
        },
        "public": {
          "type": "Buffer",
          "data": "GN5C5Rty0lE1LGHamHqfInxcEcI/P+ZvwYHOz+v3XRo="
        }
      },
      "11": {
        "private": {
          "type": "Buffer",
          "data": "wAwpCW2Z8DWrcCOcIs4kcOJRjfnBbXpAktp3u2iLFVQ="
        },
        "public": {
          "type": "Buffer",
          "data": "DU0S1jzN9oERpKIlMCVdVQTy4Fmu04Bahh34N1wqDiY="
        }
      },
      "12": {
        "private": {
          "type": "Buffer",
          "data": "YFUcD9kwylDqtGyWErzDNeo7cDtDOJukORq8IV1l71A="
        },
        "public": {
          "type": "Buffer",
          "data": "zSNV8PTaWINDBb2El7lT2KIFtzwoHSbqK76iYmDQBiM="
        }
      },
      "13": {
        "private": {
          "type": "Buffer",
          "data": "CGuz2Lk5A2RhRzts2svzj3b8n6x7Sqp43HsER5lhCXs="
        },
        "public": {
          "type": "Buffer",
          "data": "IVbbq/9lRxUv9W7cCuJobuOgavvcrcgSXngDa+yqyWM="
        }
      },
      "14": {
        "private": {
          "type": "Buffer",
          "data": "WKvzQ5W05ob2Qnp0FTe4H2NfDr8/lMf7Oxi+ZJF9kkU="
        },
        "public": {
          "type": "Buffer",
          "data": "3i5sDyo3G4+Ct+wqcBU+FrpABDn19kcr6+OiZ+X5Sy8="
        }
      },
      "15": {
        "private": {
          "type": "Buffer",
          "data": "AMUPO0xa/Y1dlp/9ZlV1HlOG4IUhFr/Mgyjr+sceY1A="
        },
        "public": {
          "type": "Buffer",
          "data": "RPRk4mJA0it4+0XFfsFXBA/gDSe846e8xZKACdALIXk="
        }
      },
      "16": {
        "private": {
          "type": "Buffer",
          "data": "SKiepyWt6hMh9Z3Y4sP+p+sb9uPMEfbbNsLhR2wGXWU="
        },
        "public": {
          "type": "Buffer",
          "data": "M05fx6+Slu/IQkNXRc5W7lslZIX7ZRf/8Z7ueILtDRw="
        }
      },
      "17": {
        "private": {
          "type": "Buffer",
          "data": "qGrO+c/FcT71mrVJ+R6pYxPWblAUGQdCOyySSWarTl8="
        },
        "public": {
          "type": "Buffer",
          "data": "L3Vru9nKXhgGI7l13DD5PwSqhnQYjY9MKZQVAVUIqQo="
        }
      },
      "18": {
        "private": {
          "type": "Buffer",
          "data": "WPw1wN/g8nOBBZHbo4T83z5WhBLr3Kk39kO1KAlXgmc="
        },
        "public": {
          "type": "Buffer",
          "data": "4tfV7HSLGhBiGkcFY7VQ84a+dOXyNgHZQ2/5fimUTyE="
        }
      },
      "19": {
        "private": {
          "type": "Buffer",
          "data": "UIEbffK3Qnz5pVEVTMETJICKVjUTAP2XMYXnARtj41s="
        },
        "public": {
          "type": "Buffer",
          "data": "+Uu++lZt15Wa14/UZ9xv1PxYDNmGOm5umJNIrQigygQ="
        }
      },
      "20": {
        "private": {
          "type": "Buffer",
          "data": "eMlujS3eGpM+rbcOrA0vtfG4ZtKkicbNUCmdFt5+hHQ="
        },
        "public": {
          "type": "Buffer",
          "data": "vf+uY5ghzszCuAh3cX7VEEfMUlZyTINqdJCPvdcVxGs="
        }
      },
      "21": {
        "private": {
          "type": "Buffer",
          "data": "uFeZ0QaSYbU8RGtWHoCp85QYXgdL/p0au6WnqAYNikY="
        },
        "public": {
          "type": "Buffer",
          "data": "Ry7jooJSYNp6C+WIv5ViQPqpL+jU5ibPkUeMx4MKBRI="
        }
      },
      "22": {
        "private": {
          "type": "Buffer",
          "data": "iPjz7bOQWuIin6YULXRqtQfEGSNeLsTKucl0Mtuctmo="
        },
        "public": {
          "type": "Buffer",
          "data": "nPf1dpricLRqKEXK7aIhL83S3bFywBcPAXPP622R9U0="
        }
      },
      "23": {
        "private": {
          "type": "Buffer",
          "data": "mMvFpxLkRr43U737CRp/nXpFZcqMTO9eWCcQh5ssH3w="
        },
        "public": {
          "type": "Buffer",
          "data": "u+VSA7f5ovSq8+jAgv4ERREnKoOQMXv+xs1iLQESD0Q="
        }
      },
      "24": {
        "private": {
          "type": "Buffer",
          "data": "4P0e4QcFqrcBDSk4lZLECnCnmLZD/PbVvnTpN0YZIWE="
        },
        "public": {
          "type": "Buffer",
          "data": "sFRQSTrjarX5LsVEhKpz1PowUzBb0ERrrzXWjfRsRi8="
        }
      },
      "25": {
        "private": {
          "type": "Buffer",
          "data": "gEwcbCTb2JFYFfoNta6VEzdhUlHagfSBRrVF6CzXHHA="
        },
        "public": {
          "type": "Buffer",
          "data": "zykmwqU+g08LmPqepDsiVfo/xDdJhRXLMmZjTtlf6AU="
        }
      },
      "26": {
        "private": {
          "type": "Buffer",
          "data": "aL9Ad8eWFYUEw88J00Nks+VKKp9sHnV/lfpacwu/RnM="
        },
        "public": {
          "type": "Buffer",
          "data": "AEZjHTJ0c36BTYrY36YI5LkM3LbIea8Ut8dlntfz6QE="
        }
      },
      "27": {
        "private": {
          "type": "Buffer",
          "data": "qIXQepchyiTvE1wLYPd1heaHc7FPJhC7bDCioVD7K1k="
        },
        "public": {
          "type": "Buffer",
          "data": "DPmu2In42CCYX2M4I2ZJZe/P+cc9pmuBHUVyLTSzUDA="
        }
      },
      "28": {
        "private": {
          "type": "Buffer",
          "data": "eGNQ3BrA+Ca6rev3x/bXA7vbLmgNTc3X0gGFEBXrB0g="
        },
        "public": {
          "type": "Buffer",
          "data": "8kGi779jP/cUJX4zIIlxmJrGgjBwQN8vP0dgQtc4Olo="
        }
      },
      "29": {
        "private": {
          "type": "Buffer",
          "data": "MEvfEns+GEpakFd9vQ64BuqA42uMsSVcj3c3ftiilVU="
        },
        "public": {
          "type": "Buffer",
          "data": "j+AAXK3HOu6By2xFUc9yynQ3SyUJxBMyPyGrpVyg6WE="
        }
      },
      "30": {
        "private": {
          "type": "Buffer",
          "data": "8NRroiYbF6MQxwea8sK6DcCUdxZdTwQdDlZaMJFQnl4="
        },
        "public": {
          "type": "Buffer",
          "data": "H+Svi4rtlbuZ0eS/Qkt+BCRbE2/KCLNM6CP5Sl8GQFs="
        }
      }
    },
    "sessions": {
      "62895335544695.0": {
        "_sessions": {
          "Bb4eptZ6KG/fD17jw1BwDgw1ycplrBTIUIQ3zaGsEOIL": {
            "registrationId": 895496785,
            "currentRatchet": {
              "ephemeralKeyPair": {
                "pubKey": "BdAwpYpsMwyNdXT4orJ5daFcszOth4NRW2cPgEo7XL4d",
                "privKey": "KD3PrHZEb57KJ19LDASttGsG1Mqi/CfCtNTfKS6kSmg="
              },
              "lastRemoteEphemeralKey": "BV1V2U1cmOh7B9qYKZ0KrLu13EApanAw7onlSoSE+Ec1",
              "previousCounter": 0,
              "rootKey": "woHHMbft9/cn4jRRXJFPUCjhqRFfUThbHfJ5JvyxFxw="
            },
            "indexInfo": {
              "baseKey": "Bb4eptZ6KG/fD17jw1BwDgw1ycplrBTIUIQ3zaGsEOIL",
              "baseKeyType": 2,
              "closed": -1,
              "used": 1669629651411,
              "created": 1669629651411,
              "remoteIdentityKey": "BVfEGTbGXy2yrOlu+KqXSG6VqpG4TKxNfzq0gaERqVl9"
            },
            "_chains": {
              "BV1V2U1cmOh7B9qYKZ0KrLu13EApanAw7onlSoSE+Ec1": {
                "chainKey": {
                  "counter": 6,
                  "key": "0IXDwPPxJ+FD+Jau3hWZY8BUOk7A+H2D98fay1o5VdE="
                },
                "chainType": 2,
                "messageKeys": {}
              },
              "BdAwpYpsMwyNdXT4orJ5daFcszOth4NRW2cPgEo7XL4d": {
                "chainKey": {
                  "counter": 11,
                  "key": "uFByjrGxFmYwf8wERi0+08BEHdaWLo5VOgGZyuQHJIA="
                },
                "chainType": 1,
                "messageKeys": {}
              }
            }
          }
        },
        "version": "v1"
      },
      "62895606423692.0": {
        "_sessions": {
          "BXXYQT8LFpORUfAVh6Mw7furlVX/cjhQ23/xyNlbMatu": {
            "registrationId": 863509941,
            "currentRatchet": {
              "ephemeralKeyPair": {
                "pubKey": "BU4H2h80oRyo5FTm9pS3OIOL1Wz/SepxqVmNeV2IdSUX",
                "privKey": "WA8MP4wn++91Ovt/ghs7VOjGPQUQ8HcXDlg3sLV+DEY="
              },
              "lastRemoteEphemeralKey": "BRXWpP4+M4vI9CdslceS25T9k1sZkzxP7BEmVXhaAjl1",
              "previousCounter": 1,
              "rootKey": "Seskl7DPMK7h44KkQ4HIoxYX62fhMjeMF6dYSn0drpM="
            },
            "indexInfo": {
              "baseKey": "BXXYQT8LFpORUfAVh6Mw7furlVX/cjhQ23/xyNlbMatu",
              "baseKeyType": 2,
              "closed": -1,
              "used": 1669629882059,
              "created": 1669629720105,
              "remoteIdentityKey": "BY+BU425714r3l3g0sUylzsfQ+dOLXkL1rkrKJtLcLQC"
            },
            "_chains": {
              "BVVEUfgw4/hqaNJF7n1ruUzQN/Raw8hCgIKbRtw9xksa": {
                "chainKey": {
                  "counter": 0
                },
                "chainType": 2,
                "messageKeys": {}
              },
              "BVQcGl4gtHBcQz0q9cTp65DJFp8lfV3WSqY1zI7OiKtB": {
                "chainKey": {
                  "counter": 0
                },
                "chainType": 2,
                "messageKeys": {}
              },
              "BXfjo2siOxzbPsSOmq9rbIMHyXvBB+qr5excVCeHE4Ev": {
                "chainKey": {
                  "counter": 0
                },
                "chainType": 2,
                "messageKeys": {}
              },
              "Bb3xeCTwAXOvPljSfwoJECFpqwtklr8Ge9Oia+PIYcwc": {
                "chainKey": {
                  "counter": 0
                },
                "chainType": 2,
                "messageKeys": {}
              },
              "Bd61FrU3GL/BeTMDuiDV00P4mF2pZC4WSAt7cNpQR0la": {
                "chainKey": {
                  "counter": 0
                },
                "chainType": 2,
                "messageKeys": {}
              },
              "BY/2StLrp33jq5xQfNSRJpY6bsgCFvmIGSO61Wl8HIxw": {
                "chainKey": {
                  "counter": 0
                },
                "chainType": 2,
                "messageKeys": {}
              },
              "BUppaROECoy/SYQz1W4j9ELPodCHAneT4J8yZd4sepNR": {
                "chainKey": {
                  "counter": 0
                },
                "chainType": 2,
                "messageKeys": {}
              },
              "BSUHznD9Y6+HcEcnvEUeFmCiy2Mbt9bwFmYccaDUW7gz": {
                "chainKey": {
                  "counter": 0
                },
                "chainType": 2,
                "messageKeys": {}
              },
              "BSju9gy//8hLWR5gclk5Pyvqb7g4ZetmVwGlCvB2wdsa": {
                "chainKey": {
                  "counter": 0
                },
                "chainType": 2,
                "messageKeys": {}
              },
              "BRXWpP4+M4vI9CdslceS25T9k1sZkzxP7BEmVXhaAjl1": {
                "chainKey": {
                  "counter": 0,
                  "key": "SjAuKcXg+bbMgwLRKBRIgeATUzw5LdHWTs6+NUlbGUc="
                },
                "chainType": 2,
                "messageKeys": {}
              },
              "BU4H2h80oRyo5FTm9pS3OIOL1Wz/SepxqVmNeV2IdSUX": {
                "chainKey": {
                  "counter": -1,
                  "key": "jVAfCm4WRPFXNZDakCDR5SBhodJlkwa/CeY4vP12gL4="
                },
                "chainType": 1,
                "messageKeys": {}
              }
            }
          }
        },
        "version": "v1"
      },
      "62895335544695:20.0": {
        "_sessions": {
          "BTVFgqKzoF5HP/1cYBN7e+wqk/VsoSyftpyB2V3QjyAn": {
            "registrationId": 32,
            "currentRatchet": {
              "ephemeralKeyPair": {
                "pubKey": "BRkDokVhYj7jurTuefNUE9fPxuR3gDY+1bl+KKALIyJW",
                "privKey": "gA9C+fUO9x3IjDzYojyrOOTVxYlatBp26cuta4TXnUc="
              },
              "lastRemoteEphemeralKey": "BTDaGleMC8wHiQJIV5AgRba6GQxWixQIZUX9GC6HoHUK",
              "previousCounter": 0,
              "rootKey": "ZtpYWbaGfJi4u8TmQMYByq0gZvePETi0fyX2DKcP1Wc="
            },
            "indexInfo": {
              "baseKey": "BTVFgqKzoF5HP/1cYBN7e+wqk/VsoSyftpyB2V3QjyAn",
              "baseKeyType": 1,
              "closed": -1,
              "used": 1669629720647,
              "created": 1669629720647,
              "remoteIdentityKey": "BfAAM8idaef1K04ZHNsOBV7soxrcrPEkEifd15lzKuBp"
            },
            "_chains": {
              "BRkDokVhYj7jurTuefNUE9fPxuR3gDY+1bl+KKALIyJW": {
                "chainKey": {
                  "counter": 11,
                  "key": "+oE1L5wmO0MoMiKoS1XmPfkjU+TML6QHDMz9090KKao="
                },
                "chainType": 1,
                "messageKeys": {}
              }
            },
            "pendingPreKey": {
              "signedKeyId": 1,
              "baseKey": "BTVFgqKzoF5HP/1cYBN7e+wqk/VsoSyftpyB2V3QjyAn"
            }
          }
        },
        "version": "v1"
      },
      "62895335544695:22.0": {
        "_sessions": {
          "BcVsEcjUop6zMIlpj989bcNaB7BvkJUyRzcgFPC9bMkS": {
            "registrationId": 236,
            "currentRatchet": {
              "ephemeralKeyPair": {
                "pubKey": "BUpW8kOu3c4S1Y7MveDzmUtVPwZ6bGyrkl7xgLiMu74I",
                "privKey": "IEZdnkjtZ9xfuDspNYNssDS/j3OozSJ108tUD4W960I="
              },
              "lastRemoteEphemeralKey": "BZDBlEUlq+izFE9IxslmS5CkFDjClLeiq8n8+Y16Rvhc",
              "previousCounter": 0,
              "rootKey": "RZFJJupCPLeFVEznQV/T57aBOqUJb+aMfqT5Z1cn96s="
            },
            "indexInfo": {
              "baseKey": "BcVsEcjUop6zMIlpj989bcNaB7BvkJUyRzcgFPC9bMkS",
              "baseKeyType": 1,
              "closed": -1,
              "used": 1669629720649,
              "created": 1669629720649,
              "remoteIdentityKey": "BQFmg53vYBuLpgeMtIvF3gCG/lxfkBClO4h61jykaN54"
            },
            "_chains": {
              "BUpW8kOu3c4S1Y7MveDzmUtVPwZ6bGyrkl7xgLiMu74I": {
                "chainKey": {
                  "counter": 11,
                  "key": "fnqkd8oP1DVJqlAHtJtrNO5I5GP0SnYtpMiufrmesU4="
                },
                "chainType": 1,
                "messageKeys": {}
              }
            },
            "pendingPreKey": {
              "signedKeyId": 1,
              "baseKey": "BcVsEcjUop6zMIlpj989bcNaB7BvkJUyRzcgFPC9bMkS"
            }
          }
        },
        "version": "v1"
      },
      "62895335544695:25.0": {
        "_sessions": {
          "BW2tLBGXf04F/71QBSykiwYNX+/KbVBDgnckgmHaR3Jl": {
            "registrationId": 83,
            "currentRatchet": {
              "ephemeralKeyPair": {
                "pubKey": "BW/Y0x0EUvypIEKfjirRQN1OufpaDXvwNPuT6LXDwc0e",
                "privKey": "GGAiVOgnZ/wHONcUP+zU7bzAPOzpoctVC2Kdqq+3amI="
              },
              "lastRemoteEphemeralKey": "BTajChsaxLERRzkYrPoclblN5jtw3uN4YmBaqO008ZZM",
              "previousCounter": 0,
              "rootKey": "W/Wxl+qDzHCFT/PJt1cDE9olJWz2U1RGB8asIF74hnI="
            },
            "indexInfo": {
              "baseKey": "BW2tLBGXf04F/71QBSykiwYNX+/KbVBDgnckgmHaR3Jl",
              "baseKeyType": 1,
              "closed": -1,
              "used": 1669629720650,
              "created": 1669629720650,
              "remoteIdentityKey": "BWgqLY+pBncUj3S2lWWBbD7bLsqjWvVAI5oDhmU+IP1T"
            },
            "_chains": {
              "BW/Y0x0EUvypIEKfjirRQN1OufpaDXvwNPuT6LXDwc0e": {
                "chainKey": {
                  "counter": 11,
                  "key": "nLWNq+pV6YS/aR58/32a/mbWToDyrilWDXJg93YzKDA="
                },
                "chainType": 1,
                "messageKeys": {}
              }
            },
            "pendingPreKey": {
              "signedKeyId": 1,
              "baseKey": "BW2tLBGXf04F/71QBSykiwYNX+/KbVBDgnckgmHaR3Jl",
              "preKeyId": 16
            }
          }
        },
        "version": "v1"
      }
    },
    "appStateSyncKeys": {
      "AAAAAMPo": {
        "keyData": "sZ28F14oz24IUvWVT1Pma16bzyMeZXEZHohYblArRts=",
        "fingerprint": {
          "rawId": 52661726,
          "currentIndex": 7,
          "deviceIndexes": [
            0,
            2,
            4,
            7
          ]
        },
        "timestamp": "1668165209424"
      },
      "AAAAAMPp": {
        "keyData": "l00swHT1qCUkLYg8J9q5yIjZNYgqZOOA6HIjMFSe8GA=",
        "fingerprint": {
          "rawId": 52661726,
          "currentIndex": 7,
          "deviceIndexes": [
            0,
            2,
            7
          ]
        },
        "timestamp": "1668213095282"
      },
      "AAAAAMPm": {
        "keyData": "z7qDN/7KDq0kStVdfiq9hGJP6F+El2mqrpEtNawxPek=",
        "fingerprint": {
          "rawId": 52661726,
          "currentIndex": 5,
          "deviceIndexes": [
            0,
            2,
            3,
            4
          ]
        },
        "timestamp": "1668162087863"
      },
      "AAAAAMPn": {
        "keyData": "5x3dN8sOZx9VZdUPB0ik7cMgms0f19GKWLfEUH5yX+s=",
        "fingerprint": {
          "rawId": 52661726,
          "currentIndex": 5,
          "deviceIndexes": [
            0,
            2,
            4
          ]
        },
        "timestamp": "1668162098156"
      },
      "AAAAAMPl": {
        "keyData": "g0AC2pkKFzDNdgXemVObqybe74+2VCa/6TWDThDlrcg=",
        "fingerprint": {
          "rawId": 52661726,
          "currentIndex": 1,
          "deviceIndexes": [
            0,
            1
          ]
        },
        "timestamp": "0"
      },
      "AAAAAMPu": {
        "keyData": "ZW82GlMxdcJauEAMJ9ti9nqkDKeumFERQmUykk9RGps=",
        "fingerprint": {
          "rawId": 52661726,
          "currentIndex": 13,
          "deviceIndexes": [
            0,
            8,
            10,
            11,
            13
          ]
        },
        "timestamp": "1669592952860"
      },
      "AAAAAMPv": {
        "keyData": "tMS77ErshNZctqqzQOy6u/HD56gKSUJvH/wZpJTUNX8=",
        "fingerprint": {
          "rawId": 52661726,
          "currentIndex": 13,
          "deviceIndexes": [
            0,
            8,
            10,
            13
          ]
        },
        "timestamp": "1669594569909"
      },
      "AAAAAMPs": {
        "keyData": "ehagPlbOaMpnXTlNI3Ul5rFe96F+7cG9zA3tyo1OBuo=",
        "fingerprint": {
          "rawId": 52661726,
          "currentIndex": 12,
          "deviceIndexes": [
            0,
            8,
            10,
            11
          ]
        },
        "timestamp": "1669591051882"
      },
      "AAAAAMPt": {
        "keyData": "IWJNBLob0WBpWrgKN/zuyVplXeRzTVnzaLN9bmMYoSM=",
        "fingerprint": {
          "rawId": 52661726,
          "currentIndex": 12,
          "deviceIndexes": [
            0,
            8,
            10,
            11,
            12
          ]
        },
        "timestamp": "1669592228232"
      },
      "AAAAAMPq": {
        "keyData": "iG839p/azNJXjyW7NGTMB5/PhMX8Z106O6cIIW+vlfw=",
        "fingerprint": {
          "rawId": 52661726,
          "currentIndex": 7,
          "deviceIndexes": [
            0,
            2
          ]
        },
        "timestamp": "0"
      },
      "AAAAAMPr": {
        "keyData": "I1N5XGPbUxuNtBUW7Lnccddy0sZVPs0Slf+Tz0V5U28=",
        "fingerprint": {
          "rawId": 52661726,
          "currentIndex": 10,
          "deviceIndexes": [
            0,
            8,
            9,
            10
          ]
        },
        "timestamp": "0"
      }
    },
    "appStateVersions": {
      "regular": {
        "version": 9,
        "hash": {
          "type": "Buffer",
          "data": "KoxShMF3TJY6PqlK/S6MlVMTqJ2K42E8Ry5CsW7c2KYIuUnY5Nn73wEeWesrONYk+hXGUz12P/INI/hCNEUau5xTGrlN8ZlhbXzpjye6sFPXXrF/WrLhpDTjuq5jF0KIHCl0DISFV8EkpJUxllH1t4pwAq1lgpS9u7xqCaqPx6c="
        },
        "indexValueMap": {
          "poyWU4pLxlcrE7A9PjzHZQ+N2vupmfoBH41KQsU5+Lc=": {
            "valueMac": {
              "type": "Buffer",
              "data": "/vqyfWp19SMiEDt2yi1DwwA/sJl0zNL1sUSid/F+Rj4="
            }
          },
          "+rLk0r9Gqv9UPix5SkR3X9YuiIMeIFxn6yb80NxW3Wg=": {
            "valueMac": {
              "type": "Buffer",
              "data": "JA65DUGJ5cJ6SrkEPweFD8zOtQATqbpPfvoJnOuUH4U="
            }
          }
        }
      },
      "regular_high": {
        "version": 10,
        "hash": {
          "type": "Buffer",
          "data": "CwSzWrpj+svcn9+vMyUK+52N74pjUpZslQK4DBab7dI7JiYZB7tsq51fyhsEV9by0+4fxgiWXRdhVuKESa4vwSuF9kOHnWlykiOU/p9P3TxkltgU1SZaKPo8GLiV1rD2yxya4hyE2IawNCU493IF3uSh+Ad5j5IgNs9AWnfGuSs="
        },
        "indexValueMap": {
          "LSwUeXhoGkDStIy73iSZF7eHt3j3YXGwP5Nz2Y/06NY=": {
            "valueMac": {
              "type": "Buffer",
              "data": "6IlJ0yGE9Gws7P2IrtV2OYa6q8QV1reDcLH9stAVRpI="
            }
          },
          "OGsHHS8LJ7vmh02uHQ1ZxxM46luMJhjijfuB9jsdujQ=": {
            "valueMac": {
              "type": "Buffer",
              "data": "qAMhszpTlQOmi7E4ShS0nX8rv1UdRQXtqWhwmNqioU0="
            }
          },
          "0B/vN5GnOcdRCkeaQDXB3tdYffjTqMHHxpYOBV4/VGc=": {
            "valueMac": {
              "type": "Buffer",
              "data": "Rq50vbCvBpB2Jh8HQodQ66gwChLMj64NMwDTHiKrXPs="
            }
          }
        }
      },
      "critical_unblock_low": {
        "version": 50,
        "hash": {
          "type": "Buffer",
          "data": "+1pTxEv12HLKdvYtTnJSHRQsXnRcPuC1QZ3YDRfjOMFpk9Rn+B3AhharKyMtYKZTy7D5ebq4Sg0zxXnTDw8UwLoYX6zPy7z/9WbiIXEZjJHJXKEMFk532X9yUOsc27/b9AbExcob7JczQlOePytiFK2MwQyOBHbIpPQpJ8eiOwE="
        },
        "indexValueMap": {
          "AgnryZjadsKtY9S4Xif672C8JMfx11gYnIoPIGUW3Sw=": {
            "valueMac": {
              "type": "Buffer",
              "data": "TFtByrn6qMkBlUJGUCqVTssWBzw5oM7NrqAkLndzCk0="
            }
          },
          "AiJFnPDw/C5KdcVSHBk4Rwthhi1iaAMMApwTpfkkE9s=": {
            "valueMac": {
              "type": "Buffer",
              "data": "e9EP/i9xUk9oBXm9mg44K+J9nsJEZ0zl4ND8eHwYxXg="
            }
          },
          "CPx/+12l8ZHAXky2utEpzisAFRzD7BWO8vCNvtaoco4=": {
            "valueMac": {
              "type": "Buffer",
              "data": "cOnwghbEDmXiGSt9RfSLSyxprM/b08UlEBGWZKo1x+I="
            }
          },
          "DyiC3heYe4A1J+yTFVecxSQU6UPVXGCqNbNFNMV3zUE=": {
            "valueMac": {
              "type": "Buffer",
              "data": "zdniUQFhjDNyv85zbhD9NRMQDVgnKHpvCht0IWQkqcw="
            }
          },
          "Fv3BhB9NWtGlPXynb6dwiPbz1XaFyMI41GGr18n/+0A=": {
            "valueMac": {
              "type": "Buffer",
              "data": "uS15/p0m6OoDQm0oukDBJ8XvHNvYEOOxYBgajt96pZM="
            }
          },
          "G37R6iqZ5i8Koi88LdbcdeWuhqYnJfUDK/AnbGC6Bl8=": {
            "valueMac": {
              "type": "Buffer",
              "data": "EilAsBKeCkMIDydDCj8yhEZLd0vSR1HvgnIgXwIt7kk="
            }
          },
          "HWK35sgB2ocWlBj66dyO9OU9mbpLUnHsSwwc+VhCld0=": {
            "valueMac": {
              "type": "Buffer",
              "data": "MmZoVNJNR+OdSykNF/ieY5HR+m5BoCTqLSqCD/rXYSw="
            }
          },
          "IeT7zjRAfAzuiZGqE2qcwG6EJfpI/DqwTXdWG+ud1Dg=": {
            "valueMac": {
              "type": "Buffer",
              "data": "3Xl0pclOkfg5WO20+xK0Bsd8UekYsB21NZ3YM71y2Ok="
            }
          },
          "JrsFssD0VHLPNcy0iiIzVLXbFA1RoeU3deQk0K9kgl0=": {
            "valueMac": {
              "type": "Buffer",
              "data": "Z0FgHaDhyl66NTRDVwYWIjuvzvF2TkOKgpkETcrGhiM="
            }
          },
          "J1BYSapnNYWMSMNDQxWq45St4k8v22eecb7Dh/O5EGI=": {
            "valueMac": {
              "type": "Buffer",
              "data": "VfCeDVVQW7I/cr+GhdbjeOhOiUgFbXpNQxAmiTFAhFg="
            }
          },
          "KlkQGVCx2brUTDKoL8Q4GORf7p00brUxPy1WPW5k4YY=": {
            "valueMac": {
              "type": "Buffer",
              "data": "Mmk8f1AEKvXvVhIbcdPxkWj+5nSYoy30cp1M0K4BReA="
            }
          },
          "KnzAGHuQzhWXQ32+2j981LfzU6nz+Rb8oVdf7FxjO3A=": {
            "valueMac": {
              "type": "Buffer",
              "data": "cUdd+B77JjUJNrr3ZS4CDWxi95yq7sPaTX12sWm3qgM="
            }
          },
          "K1Yax+D24TERBKCBH+L4/s/Cl8wj3DLtleYD+mhQQ0Q=": {
            "valueMac": {
              "type": "Buffer",
              "data": "axijUSuMXwC+xIKC9SfCEne026SR4WKKzhJywZpwnhs="
            }
          },
          "MXWXtSnuFGZqVaYH291/3mQH0i/xYIu1ECj9RlaW1WM=": {
            "valueMac": {
              "type": "Buffer",
              "data": "6h22106aF9RyM5jRnhP5lq/KYdDzq7nzjAZNvS8dimk="
            }
          },
          "MgLJI6R5idHlMPWwoL4W1Qc/BTkBn67NNlTwQeqdMmU=": {
            "valueMac": {
              "type": "Buffer",
              "data": "7HHSfN/MwqkMkdXRmFnBII1g6QERrSDKcUqBGBmy8+8="
            }
          },
          "Mw1KWDkwhOwtY8oX6yYieLMZR8FTfAelT/0pPSegbnw=": {
            "valueMac": {
              "type": "Buffer",
              "data": "KrmPIHeITMLWMf1CGU1/qwhGNJ1KMoe6ez8aG7qeeBs="
            }
          },
          "NdfXCeu7FaNdtiCH7qbHNJ4r0iaoHyKEO5XOW9HocT4=": {
            "valueMac": {
              "type": "Buffer",
              "data": "e30IhVx582nEan9+Xkw0+U46goAAcBZS/W2TqKFpnsA="
            }
          },
          "N/RW5u0AbW+WBiFxdqNUypS0Tf5C5smTKMKvM4WleQU=": {
            "valueMac": {
              "type": "Buffer",
              "data": "zfnI2TxB5QXoWFr4e8el6H6Hqe9UUvw4B1lB6E56d5A="
            }
          },
          "OGtdwdhMFM0EUiZfp58k9zr3pVIu1lYDWUqpUNoHuM4=": {
            "valueMac": {
              "type": "Buffer",
              "data": "eSmrNWnr0yKLmoJiRNfGQ2hKvFLelDXuB+wgmHItAM4="
            }
          },
          "PofA2l6Psczy2v2Gsmfc7Xj7f7S5LRwS5voYKN72Qsw=": {
            "valueMac": {
              "type": "Buffer",
              "data": "+T0Aa/NDaBwkNESpen0Wkcpmnm+sp+0ye5wCADIb3qk="
            }
          },
          "Rhw+02EVAZjoDdglY2GOzfLuxRHlc/OZfnu9LQw9AXk=": {
            "valueMac": {
              "type": "Buffer",
              "data": "i3Gtn5RM158eo2zeR3VqMXvneB+Tl6EtzW8NvWafcoY="
            }
          },
          "Sb6NhUXe/MVKtE0oYrZwnafb3iPT98sQawuUm0NEbTQ=": {
            "valueMac": {
              "type": "Buffer",
              "data": "4PLx5splzJp/+pTR0jmomB9h9wPY40AQYX6vcoVw048="
            }
          },
          "SlzftyeEtymmdWzACrH9w0r2W1veyrCvmsAJF5jSb64=": {
            "valueMac": {
              "type": "Buffer",
              "data": "A1SqVQSPy2luiBCjnAGudpW8YbjCgG7ZrgzZbq3afdg="
            }
          },
          "TKDgwFq6RuvBUK1/RHEEXVnTquF/2JLUgXbaIY0KWp8=": {
            "valueMac": {
              "type": "Buffer",
              "data": "KDaH/rHKzU4hQasQ49JUgR6rDhVytEBIQfXtv0W3Ejk="
            }
          },
          "VO6GBjUIF3XdZsYH0qgE9LH+xBoenONPcPe4BuUa9rM=": {
            "valueMac": {
              "type": "Buffer",
              "data": "ZkVu3bjcezwQztmaKSd05B2agHEdwUbe7OuteLViJho="
            }
          },
          "XFCV5LBd2Tg1fiGOOuUKZB7Ypoc5YbYyplii+HOgplw=": {
            "valueMac": {
              "type": "Buffer",
              "data": "f/FFU5yBjMTgjj5XRlyTXWu22Omq0AuTT15oQARHUjw="
            }
          },
          "X/KGAznRL0BEtD5Ks6oCX0H8lbywFX85+CN7C/ecASE=": {
            "valueMac": {
              "type": "Buffer",
              "data": "DiDo5X9XpfOluhh6gOpkxbV0MHvSVIVyqHH2sJm6g5g="
            }
          },
          "YNHdDCxmef7ZmAXhUhR1XP+kMCb4j8NkGsbE7CbwjsA=": {
            "valueMac": {
              "type": "Buffer",
              "data": "03xXIHmAl02z+sB744A37RPEo63eD1X0skH73OiZM9o="
            }
          },
          "YgKXnI3TkufmcdhL0a1fSW9daCo98t9Ubjc+2xpYFPw=": {
            "valueMac": {
              "type": "Buffer",
              "data": "MSh0lKNrBsuO4aIbdU2jspqVIdXk5HU2VABy5WIeqLA="
            }
          },
          "ZHvoS2zMVtZd0JK/fUu9k7X/K2Z8DTx6MWQ1YPYkstU=": {
            "valueMac": {
              "type": "Buffer",
              "data": "eApJoblZ+st8Wqry89k5Pv6QjsYtFRJBEmAGl13AK4g="
            }
          },
          "ZkkVHR/T+PiXdwCq6heFf2hjWnad2UPpl9tF2pJRgsI=": {
            "valueMac": {
              "type": "Buffer",
              "data": "tLH4Zfycd2On/M7ccXglUeQo6KL5av9QzQEz7xDlGFU="
            }
          },
          "ciRg2i4lyM/6nNnQ6gCwiHAado+zTQKWayijw48xHzs=": {
            "valueMac": {
              "type": "Buffer",
              "data": "JEUnvNYZLm7JH5NsxJeS55WnKogdHCOBEymOWWaXLJo="
            }
          },
          "ckhumn+MJv3GZNNi3B2qg/arLylZsa2Q9V8wuUo1+00=": {
            "valueMac": {
              "type": "Buffer",
              "data": "/l5w0fZbCIEGSj3ulAybSsoFYUVDmjRGaijcDBkETBs="
            }
          },
          "dAgvHIfYrK0AFqYXWlMlEZKarCKB4hgYYuXXQgszlIM=": {
            "valueMac": {
              "type": "Buffer",
              "data": "axi1I259T6/tly/CH1FB0LNIC27e+A3nKvbQ+tlS+nQ="
            }
          },
          "dl7kcwR8itTeuD+g0Wj8LRCht16RlvH4ReWersZhRk0=": {
            "valueMac": {
              "type": "Buffer",
              "data": "ym0xxabjhQzzPEaS9sz5dqkGbE+ro33llGHFjTQ3nfo="
            }
          },
          "eTFzX8Bpa0AHCXEu5MMI5rzdddPFD5t5uAxzyLu7bIE=": {
            "valueMac": {
              "type": "Buffer",
              "data": "gN9fC99LcwMncBwNRyutxalAfrJx6ZflGjeWfFgTrb4="
            }
          },
          "e4HXkaAON4mqoGo8Efq1vL4re1RV1xHganoTSNnVpTE=": {
            "valueMac": {
              "type": "Buffer",
              "data": "ozo3L8v0sKdTC0JegaazvRfQ1pKwOdjfGgKkZH3k8CE="
            }
          },
          "fBFsulqAmwuHxrECzzDZksdWAUfhOdtR8/kauddVf6k=": {
            "valueMac": {
              "type": "Buffer",
              "data": "BlfYDyCe6UYPSnDiaCDHTH/7ZO03UmZQoCKh1gu/Yjc="
            }
          },
          "fK3gE5CHEl2E5GZqDq6B+r7pU4ztOty4u6BZcTahggM=": {
            "valueMac": {
              "type": "Buffer",
              "data": "NEW+2ntJnTucZS6AT9OKdL9g1TvTq1B0NHJgHwkd/g4="
            }
          },
          "i0jZao6tmML9kS8tf6EJpBmk8FaLP2UkI0d1EIaQxLg=": {
            "valueMac": {
              "type": "Buffer",
              "data": "PRuBm51uK2kZIudXxCzv4EBq9yXvAjJwnhy0xbN731o="
            }
          },
          "jhkjl1ldESJe3fUeTAawZmsdioeXs2n4OsC2BZBkFno=": {
            "valueMac": {
              "type": "Buffer",
              "data": "5ZVQXSqCaFGXogAc83fA2OIcXJYmUTx+DLdzBsuT35E="
            }
          },
          "kW2SUwihHTyZdeBD4QnpxxLgKV5axeExeLKMDBWhCVo=": {
            "valueMac": {
              "type": "Buffer",
              "data": "y+ACcO/h6Fzz12grwpVBFGBwulzSojmjgXWkd7FCyIA="
            }
          },
          "lDtTYfz7hPVFBTKMG/Z14wn55lWghvI99atMf3kvGjc=": {
            "valueMac": {
              "type": "Buffer",
              "data": "Tt+zgMHkyDlDLi1Xa80qDth+tVSYlhIT2QNEBwC6QlA="
            }
          },
          "mLavw7Tnh3dhuuMW9j/k5rQLvUjK1Nz1dN5I95TxqEM=": {
            "valueMac": {
              "type": "Buffer",
              "data": "gqYgN6q8uXSvycsu89jrUtWsTzxSd3NjPM6AriQ7/+Y="
            }
          },
          "nTqBn/yBsY5CTbYGu/8APS5+11wDu7FuoSkbF8P5UGc=": {
            "valueMac": {
              "type": "Buffer",
              "data": "V2DQZq/NQAm5cl14NFjMtTYnbrRoY3xiIe0IVpUIJV8="
            }
          },
          "nU0RPNj0o8LZSO4xOQPnK/k0ZHVksAW3xzZoP9tzbak=": {
            "valueMac": {
              "type": "Buffer",
              "data": "2r7H76g1Ir8/XA2QhBlsIdCAwIQYDyB04pDRTOcwArg="
            }
          },
          "nlS9Xg8gcvxBS7ixwncAV4PiQyY9A4XTz89VgUXN+V4=": {
            "valueMac": {
              "type": "Buffer",
              "data": "VFci1ogsxCYG0FSJ8x2OI6eGvRKMe/hFnlpKrmLa7IU="
            }
          },
          "oXQmfgjmxIgxrJtN4ZmoRYDjV5RIi2AIT/IVaBnI1DI=": {
            "valueMac": {
              "type": "Buffer",
              "data": "Y28vNGgciqUqb+JDCf6X4nkOoqkHHP20a636Vns9NUc="
            }
          },
          "pbZPDVX5tpon+45jCLpRT9Chq3QIDrsCjU78nL7o/oY=": {
            "valueMac": {
              "type": "Buffer",
              "data": "noyDeZtLOt/TJPeKS/VRLua2W3uUojl6dio7YH97dAg="
            }
          },
          "prZ2Mdz1o7FZPk6SaqoCyskbu9iO/PtusFdo43peIN8=": {
            "valueMac": {
              "type": "Buffer",
              "data": "iMqKK0Hya0Kj+cWT2TMBz7I9rskhPw8qSxPHRWVsUxs="
            }
          },
          "pw3IsbmkBevDtNpMKkB/gnnHCluQmO8Gl2Js4qwbCa4=": {
            "valueMac": {
              "type": "Buffer",
              "data": "1vKH3Cf1D6ryDSPmRSY/lqF2hNPIa9mR8Km1owq5/qs="
            }
          },
          "qggfjKAtM5SZR1Sva5espuSb23Trxt/oVAneJi+cLxI=": {
            "valueMac": {
              "type": "Buffer",
              "data": "YnIvoLiz/RePAJ4D5mZBOtI0z+Mqf3zvE+LexG5USQI="
            }
          },
          "rutMZT4kYtLyu6gmntVdqXuFpIBYdopmAICQ5aXVAQg=": {
            "valueMac": {
              "type": "Buffer",
              "data": "dyr1bqk293rRJTZIfvSnjuElrOu7Z8YsfWM2NbnVvdc="
            }
          },
          "r1/uszW/t14kaBcW85mGKTPhzwbQtnsQGm2um2XRdNY=": {
            "valueMac": {
              "type": "Buffer",
              "data": "abo0ywCwXEz6o1mT1bMxhjs3yOcy15sL6xRUwSc/J+w="
            }
          },
          "suupwBYisMlJ5VJxAEZUDGP3QWkD7sui62Ov60l2BNE=": {
            "valueMac": {
              "type": "Buffer",
              "data": "9DfaD9FJ2Uyx5bpOPDT/tnzNDfnp5di+saMS1pOixHo="
            }
          },
          "tAYq4nmcFCVA5L3IfkfcuTaTwO4eRRHg2uMGLAOaf6s=": {
            "valueMac": {
              "type": "Buffer",
              "data": "w+E/OduFEen+5Qima7Iuo1Ar6wuDDDAhnHVenXFSb60="
            }
          },
          "uBAh61MUtViH7kBOO4gM7TuO51hPrY7CwxaLy33yqNA=": {
            "valueMac": {
              "type": "Buffer",
              "data": "U+u82wO4hM3vkbZrd4R+MPirrZJMkPDXl4pP3sn43QU="
            }
          },
          "uBafYkvB+thb2RBpuvb29fiNo7OUzBqxuJ7W72jdOh4=": {
            "valueMac": {
              "type": "Buffer",
              "data": "F4qZ7CBQcoTTJoNlyfxdMKYqViMP2B4UWEzCTM6mJ78="
            }
          },
          "uUg4ndc5c4WqaijfXNb3Gs1HadTJf2rVlhqyn/MNsok=": {
            "valueMac": {
              "type": "Buffer",
              "data": "xEgtcnMz3eYj7fl/bFUqhB7MenUIHDSdDZPyuAxHayA="
            }
          },
          "uxniOMkXEYsFGCFB79Qgu09tuBRkx+f5HgmZyNOr8pw=": {
            "valueMac": {
              "type": "Buffer",
              "data": "uCDxNHaTIFF84YzJe1G2SxvbfJg5y1KnsiWPU67Gp30="
            }
          },
          "vKMdudV+qg0rIXEFOo8tlYnpyfQBBXyBm+kQf9w/n2c=": {
            "valueMac": {
              "type": "Buffer",
              "data": "tckg49YFnzjOWu2GrAp//YJGbMTg3krDnHz8LbRxS5g="
            }
          },
          "vqprbffpKdQKeC+7XFqTT+zsmhnOyk529ToGKNDZZgY=": {
            "valueMac": {
              "type": "Buffer",
              "data": "kFQDYoGP3dTitmXadksP9BePg3wn5BWztUfKTX2wUYY="
            }
          },
          "vytTpH3xLsFmS84v5jzDQUg357kZ6YFKEpyvyIacOjo=": {
            "valueMac": {
              "type": "Buffer",
              "data": "HM86t8U6VZplIod3aQ184F9PMTSdOuMd3kPgt25/rKI="
            }
          },
          "wnaO6tJ5kaszWql8PaIjKeSL0VY/WYnqD5q6rLX0ens=": {
            "valueMac": {
              "type": "Buffer",
              "data": "AjKQVfJy7cMC0bLnrgPKxJrr8jYJ34Yyw7siyeVcp2c="
            }
          },
          "xCEMgExwSJH8InyAHtimQTYWek9gUnX2AS4cXVFZcOY=": {
            "valueMac": {
              "type": "Buffer",
              "data": "wUSxmo2WKBRDqDXGZdNnSireV0FmZNjZ2Sim/AqQqKA="
            }
          },
          "x8G39is8a7nSVoHC1o/YLtHa4tqFFArpwJqcDWWGaKo=": {
            "valueMac": {
              "type": "Buffer",
              "data": "9VzY57Isho6ydlLJEPiF8OS5lqyvymCWk0khAufESSQ="
            }
          },
          "yO5SMgPZ/3On82uCjS2nEeSlZTibhlk8pta4ioI79mc=": {
            "valueMac": {
              "type": "Buffer",
              "data": "bWkemII5yxPJk/tbGdSp2Clq/Why4xGKlKhzmacYAe0="
            }
          },
          "yPT4rQ+W0IjuD1jnoqKqALRZLLm4UUpap/PIK4z5Krc=": {
            "valueMac": {
              "type": "Buffer",
              "data": "jkFHLIJnuxK2cVfaQhNXm/vXA14LbsmONTileGKEP3Y="
            }
          },
          "ySzchb6jV2n4gpf88lexUeuqMiKjfLrW4UsJKkmsE/0=": {
            "valueMac": {
              "type": "Buffer",
              "data": "kXf880GXgHKtsitph0Utas8YeQ9QI6veXaZb9wZfjeQ="
            }
          },
          "yjAlchoMpEGl7jhhlcxpjT041SpG83iAyqpa5oxlUOY=": {
            "valueMac": {
              "type": "Buffer",
              "data": "HuquRegrA7NGlgXg6PUKnXkk5joxv7iYi2++WyPSRXk="
            }
          },
          "z6pxItb9KddkD0bzJ1IO9QEyBFGgamBl6hHQifZsYps=": {
            "valueMac": {
              "type": "Buffer",
              "data": "Ih9Mui9J6khoJzpCtPgiDw8z1OcNMIy5le8OR9I/EUw="
            }
          },
          "0rxgHn1bqpd74FEGGAOPAM4iMYaPI8aHhO/xGv1Qd7k=": {
            "valueMac": {
              "type": "Buffer",
              "data": "IsmPhzkx747eMovvtrP87K/slfyGgA8/1kYD4XARPMc="
            }
          },
          "1XvxV85W+k2D5ULZgH+Xn/bUnyQjd9b2DqXafJr1xTA=": {
            "valueMac": {
              "type": "Buffer",
              "data": "MOsAjfh7S2Wek9PKZ9gizxQzB/MU4KtZhLmkuyREtw0="
            }
          },
          "5HdUkz3dgKbrgslvCfCvnlVI3dbfbB0N+QM+Cu0L1Ik=": {
            "valueMac": {
              "type": "Buffer",
              "data": "InisLk+5nQ0TwqlhPDIsgW2CtNKosJ45B7jrcyWOvs4="
            }
          },
          "6IoBdycapZP7AIwll+A+HmizobKI80Ii4CwQxajxCUI=": {
            "valueMac": {
              "type": "Buffer",
              "data": "oW9M8TXWsDGaiXA9oh2DZF/MUmDCoKopj6bELtEijro="
            }
          },
          "6dUTcya3VpHTWwdncKoC1VNjju9WLBHI8KW4rGjzDQM=": {
            "valueMac": {
              "type": "Buffer",
              "data": "+e5HC+nzLR2hFcQyXsBITQZ6s+40/Z8Cmo4Tx8IK/Y4="
            }
          },
          "6l6wjzwwy80dxYPrMVSulThvBcePDpW2TLQW82dSPr4=": {
            "valueMac": {
              "type": "Buffer",
              "data": "U59f/aippWsxI3fm993BGkVz3Bu4keC2KLCopmMQoYA="
            }
          },
          "61noHCMfbb6doVcLG8tth0EcIXNZseqz5G/Z7bHap6c=": {
            "valueMac": {
              "type": "Buffer",
              "data": "V0yKlMDipguhnNDCWU6c+VXrInrw4w+uQX5xZYXJ6iE="
            }
          },
          "77b+KymFo+TYhA0DARl3xo7xrUP62ydhkRpwqTRiCY0=": {
            "valueMac": {
              "type": "Buffer",
              "data": "4X6+ARz7MXJY7dmQ0RubQB96ZwiWkpLEWkP8X7ZZQJc="
            }
          },
          "9XHnAMIX2ZitNEy+feWMl1kA6ICneLksqV3ZyGyAmE0=": {
            "valueMac": {
              "type": "Buffer",
              "data": "v6Q7rqclYQROQIAnBO6xK4HBJ5C8/m54r2bv6HNjhM8="
            }
          },
          "/YKiFfwKSpL41eRJcEAYicnrUe8J/FvWiMrtC3nd9w4=": {
            "valueMac": {
              "type": "Buffer",
              "data": "RUCJjlqWhSEypQCZR1AYK18UYZiqtw6LXSc9yacvO+g="
            }
          },
          "/eO0BO43cAtG7uAWvyar6YFnCbNxC2tY/xP2VIkByu0=": {
            "valueMac": {
              "type": "Buffer",
              "data": "U4CXOqZtnITvYPCuvPnCy+52aRsEQ8FBzsiLYUYlyt8="
            }
          },
          "/fWywAg3/BENmxrLlOle+XtD5pzBh1sv+/j9FeI7YcI=": {
            "valueMac": {
              "type": "Buffer",
              "data": "pGuFX5+YhOE5yH1AlRNp8uVNdD0dkzFW2mbqsVmyFJ0="
            }
          },
          "/nM7f/YYFXhSFIt3V6m1DHADO0qOcKIq6BK1ixOXkKQ=": {
            "valueMac": {
              "type": "Buffer",
              "data": "sl4v+BY+F5spptZvqgX/xutErgPyGgMnj2sk9AhNoJc="
            }
          },
          "RWMm3P9HBgDib2kFuqvd7+ybPogqAR/5nycLJUWYBN0=": {
            "valueMac": {
              "type": "Buffer",
              "data": "zKYwqqdVz1Yo7dMe+4LhsPIR14f7Vhg6A9ZpiXYwO5s="
            }
          },
          "+XJ7jQQP3SqHbtMA8TdrXhGJJeA3ckr1WOANEZyqMgM=": {
            "valueMac": {
              "type": "Buffer",
              "data": "hoB94+yYTrB9QHb5bH1pq3fDzdok8INnjvhNYc4eUgo="
            }
          },
          "TKmqk3VGgjA5T5FmJm0wqOX6nxAAAEyO8yfgOIEiR1s=": {
            "valueMac": {
              "type": "Buffer",
              "data": "rCvOO5n25zsxt4QAo3ryxRiUl/gIWJeLo3lV/GIQM1o="
            }
          },
          "UqjWxJ3GJslNrHy11d7uiwhpjReLwJf66fpx+k4Y8rc=": {
            "valueMac": {
              "type": "Buffer",
              "data": "Dsr9RP3oUpr2FXW/eN9gmquA4Gm4bxP4n6oKcenftC8="
            }
          },
          "Dts46N0f1kPEPFCzy/xkQhK+cOfJ4vRm15R4mXfVklA=": {
            "valueMac": {
              "type": "Buffer",
              "data": "Nx6H2lyzuo3OkZyShAL+7EWOmW1myFD9niJQTTl4AZ4="
            }
          },
          "MYmG8VVQAhY4ZM0Px+6rQU8iAfbPLqTu7rUKxEUihQM=": {
            "valueMac": {
              "type": "Buffer",
              "data": "ePhi45jtN72dcPd815n9LH/BCOxm6n0/ea504/Jgrmk="
            }
          },
          "qUBCZkcE9eTnpO0iqaz63TIukIaWiovfhQuGvc02jRg=": {
            "valueMac": {
              "type": "Buffer",
              "data": "KD2z2g9vXGMUQ5K5XxUUCEsTKdJ3aXausqMiIdE4bqQ="
            }
          },
          "sZ9dKVXQAWfxAmaAZJGF9fvJz8c+p/9IRdSFPRoXfLs=": {
            "valueMac": {
              "type": "Buffer",
              "data": "1E1oxqe+IFUacYYrgxg9pCEjSiXAsaxzC59D4qP0+34="
            }
          },
          "YP6Gu034z5rAT2L0oceHbTGxXBLeOoKHRZpJLZ8CXh4=": {
            "valueMac": {
              "type": "Buffer",
              "data": "7g8VdOVjzfY2dQJdWJdOv2wpqjrx40+4rQa8rGAYXG0="
            }
          },
          "HyeH+8bclOa1L4cj2vYtvFGeOqQ6oIIWDTEe3uEhKss=": {
            "valueMac": {
              "type": "Buffer",
              "data": "YrAOwMoUSmh7ul8+YaO+37+Bl8lDJUxntpeC7heYTUc="
            }
          }
        }
      },
      "regular_low": {
        "version": 11,
        "hash": {
          "type": "Buffer",
          "data": "GTgjqG4xQS/+MySCPvKFBYDQmrbMHIjCJPHDg72LNKtP28GQR1wzNHDaIYvCVuNR2Jq84HLcjYY6wZeV9sTF0MuFPfbVIWt71+Fx5chXc7wEBXlo1dAvZ5TDlWQYCIqW4QOMKRkfPRz1oyqTGyrYHBiUrAxEN5qy43OeJ4fFY6I="
        },
        "indexValueMap": {
          "AR77oumxbfo3ewMB2VBQtDXYpkNwqw0I7I/I/Hq91sk=": {
            "valueMac": {
              "type": "Buffer",
              "data": "IVuJeG9MJ0OiFj/YVZIhT1F+HzJJ6vj+1yIOYGd58Y0="
            }
          },
          "CaE1/xA0m1HSspKcrel9CZR0DLWA1sg7CCq4VRAA0tM=": {
            "valueMac": {
              "type": "Buffer",
              "data": "R2TGv1JFDc7+Rdlpjcsprj7yiAFPGCCz4VmjuIf3GUE="
            }
          },
          "INXJu3bthf3bhoHHibjcVtOd5+vAfZJQySDCqdpWjqA=": {
            "valueMac": {
              "type": "Buffer",
              "data": "r3ONR30p0RFTXxYvVS0eo6mFI5JiFgHRQGpqlbUUB1o="
            }
          },
          "REyGhPjcbQu+3VmobfvznZAfcUZ2+JltCP42Htu35GU=": {
            "valueMac": {
              "type": "Buffer",
              "data": "wd+oXhcB1WvzQIf0uUnATwi/PpLLt/HCUlS0ERZlem0="
            }
          },
          "ly4TfA1wqY2BTfUbQ0QizZpOtpKy8oO+uLh9UOvD6j8=": {
            "valueMac": {
              "type": "Buffer",
              "data": "6MnWm6j5zeQ7hYAIF8qQ73yMyxMmoHpJsOIcc2CO6u0="
            }
          },
          "uiOsEWXa20Al2OZYi5NlEChOSJkatXKG9TDyDueMpDQ=": {
            "valueMac": {
              "type": "Buffer",
              "data": "cpQxRDwoDtEBjPSy17KMpxwffNXDJ4/0oYdRvhVvMP8="
            }
          },
          "7tEkwD4CyWRWe2LASzUF5APvuqzlQwBelT133pabkFA=": {
            "valueMac": {
              "type": "Buffer",
              "data": "5DZIF5g3H6wajtuB9TRUXVpGTESOlPYEIm/T5fGUr6g="
            }
          }
        }
      },
      "critical_block": {
        "version": 11,
        "hash": {
          "type": "Buffer",
          "data": "XLUSCH4Um5Ifr7EvOCRuLd3sf5ba447erUKtd1uk5xOyphXImGxBU1OZOraPyk9VU5GqhickIh/QsFNQ28e/vkaGeOlSDSaT4M1l8kM6nDCu4nHUTnbHYgZdbyaYdY0n6vnVGvje93817OKp/dJEk9wqEnX5QrXqnz4kt4dwwC4="
        },
        "indexValueMap": {
          "dKiD5kuAU9ZACM513rSTZWlPVCKlK1Aw8ENnmPCSxeE=": {
            "valueMac": {
              "type": "Buffer",
              "data": "A4xlc4dJtie3f8P9I4sGgrDoFS2WkoCwGa59S2mAc3c="
            }
          },
          "goK9zWI5Kez+qSeaONTQovCSFZVOjJtF7N/XllK0jaI=": {
            "valueMac": {
              "type": "Buffer",
              "data": "AwX3Y7LQ07chSA67Eo5jlNZ31qgNzqGRygEKWDMNVXg="
            }
          },
          "/ZDhs2B6ztCqnHZ0GKY/5nH4txxGljc8cIk15rScj9Q=": {
            "valueMac": {
              "type": "Buffer",
              "data": "036K2J/xHE8j/khucikglnwoN8ZP7+enThx9beVwc/8="
            }
          }
        }
      }
    }
  }
}